pylic/__init__.py
pylic/__main__.py
pylic/__version__.py
pylic/config.py
pylic/license_checker.py
pylic/licenses.py
pylic/main.py
pylic-5.0.1.dist-info/METADATA
pylic-5.0.1.dist-info/WHEEL
pylic-5.0.1.dist-info/entry_points.txt
pylic-5.0.1.dist-info/licenses/LICENSE
pylic-5.0.1.dist-info/RECORD
