Metadata-Version: 2.4
Name: pylic
Version: 5.0.1
Summary: A Python license checker
Author-email: Sandro Huber <sandrochuber@gmail.com>
License-Expression: MIT
License-File: LICENSE
Keywords: checker,cli,license,spdx
Requires-Python: >=3.9
Requires-Dist: license-expression>=30.4.1
Requires-Dist: toml>=0.10.2
Requires-Dist: typer>=0.15.2
